setup.py
src/boreas/__init__.py
src/boreas/applications.py
src/boreas/commands.py
src/boreas/server.py
src/boreas.egg-info/PKG-INFO
src/boreas.egg-info/SOURCES.txt
src/boreas.egg-info/dependency_links.txt
src/boreas.egg-info/entry_points.txt
src/boreas.egg-info/requires.txt
src/boreas.egg-info/top_level.txt
src/boreas/api/__init__.py
src/boreas/api/debug.py
src/boreas/api/handlers.py
src/boreas/api/urls.py
src/boreas/client/__init__.py
src/boreas/client/api.py
src/boreas/utils/__init__.py
src/boreas/utils/tokens.py
src/boreas/ws/__init__.py
src/boreas/ws/controllers.py
src/boreas/ws/handlers.py
src/boreas/ws/urls.py