Metadata-Version: 1.0
Name: boreas
Version: 0.1
Summary: Websocket pub/sub server for python
Home-page: http://boreas.readthedocs.org/
Author: Karol Majta
Author-email: karol@karolmajta.com
License: JSON License
Keywords: websocket pub sub pubsub
Platform: UNKNOWN
